<?xml version="1.0"?>
<!-- The COPYRIGHT file at the top level of this repository contains the full
copyright notices and license types. -->
<data>
    <xpath expr="/form" position="inside">
        <separator id="aeat_303" string="AEAT 303" colspan="4"/>
        <label name="aeat303_post_and_close"/>
        <field name="aeat303_post_and_close"/>
        <label name="aeat303_move_account"/>
        <field name="aeat303_move_account"/>
        <label name="aeat303_move_journal"/>
        <field name="aeat303_move_journal"/>
        <newline/>
        <label name="aeat303_prorrata_account"/>
        <field name="aeat303_prorrata_account"/>
        <label name="aeat303_prorrata_fiscalyear"/>
        <field name="aeat303_prorrata_fiscalyear"/>
        <label name="aeat303_prorrata_percent"/>
        <field name="aeat303_prorrata_percent"/>
        <button name="calculate_prorrata" colspan="2"/>
        <newline/>
    </xpath>
</data>
